windfindr/__init__.py
windfindr/utils.py
pywindfindr-2.0.2.dist-info/LICENSE
pywindfindr-2.0.2.dist-info/METADATA
pywindfindr-2.0.2.dist-info/WHEEL
pywindfindr-2.0.2.dist-info/top_level.txt
pywindfindr-2.0.2.dist-info/RECORD
