Metadata-Version: 2.1
Name: pywindfindr
Version: 2.0.2
Summary: Library to communicate with the windfinder API
Author-email: Wesley Menezes <www.wesley@gmail.com>
License: MIT License        
Project-URL: Homepage, https://github.com/w35l3y/pywindfindr
Project-URL: Bug Tracker, https://github.com/w35l3y/pywindfindr/issues
Keywords: windfinder
Classifier: License :: OSI Approved :: MIT License
Classifier: Programming Language :: Python
Classifier: Programming Language :: Python :: 3.9
Requires-Python: >=3.9
License-File: LICENSE
Requires-Dist: httpx (<1,>=0.23.0)
